Workbook

Sheet Menu
A1: 📋 Organizador de Imposto de Renda
A2: Clique nos botões para navegar. Preencha as abas na ordem sugerida e acompanhe o Resumo.
A3: Abas da ferramenta
B4: ➜ Contribuinte | C4: 1. Dados pessoais e ano-base
B5: ➜ Rendimentos | C5: 2. Salários, aluguéis e demais rendimentos
B6: ➜ Despesas | C6: 3. Deduções: saúde, educação, previdência
B7: ➜ Bens e Direitos | C7: 4. Imóveis, veículos, contas e investimentos
B8: ➜ Dívidas | C8: 5. Financiamentos e empréstimos
B9: ➜ Checklist | C9: 6. Documentos reunidos
B10: ➜ Resumo | C10: 7. Totais consolidados
B11: ➜ Listas | C11: Apoio: listas suspensas e parâmetros
A13: Links rápidos (oficiais)
B14: 🔗 Receita Federal - Imposto de Renda | C14: Programas, regras e prazos
B15: 🔗 Portal e-CAC | C15: Declarações pré-preenchidas e extratos
B16: 🔗 Meu INSS | C16: Informe de rendimentos do INSS
B17: 🔗 Consulta de situação cadastral do CPF | C17: Regularização do CPF
A19: Como usar: células amarelas com texto azul são para preenchimento. As linhas de exemplo (linha 6) devem ser substituídas pelos seus dados.

Sheet Contribuinte
A1: Dados do Contribuinte
A2: Preencha as células amarelas. Dados sensíveis ficam apenas no seu arquivo local.
A3: ⬅ Voltar ao Menu
A5: Nome completo | B5: Maria da Silva Exemplo
A6: CPF (somente números) | B6: 00000000000
A7: Ano-base | B7: 2025
A8: Data de nascimento | B8: 33013
A9: Possui dependentes? | B9: Sim
A10: Nº de dependentes | B10: 1
A11: Declaração conjunta? | B11: Não
A13: Legenda: célula amarela com texto azul = você preenche. A primeira linha preenchida de cada aba é um exemplo: substitua pelos seus dados.

Sheet Rendimentos
A1: Rendimentos Recebidos
A2: Registre cada fonte pagadora. A linha 6 é um exemplo. Tipo é escolhido em lista; valores devem ser maiores ou iguais a zero.
A3: ⬅ Voltar ao Menu
A5: Fonte pagadora | B5: CNPJ/CPF (só números) | C5: Tipo de rendimento | D5: Rendimento bruto (R$) | E5: IRRF retido (R$) | F5: INSS / Prev. oficial (R$) | G5: Informe recebido?
A6: Empresa Exemplo Ltda | B6: 00000000000191 | C6: Salário / Trabalho assalariado | D6: 60000 | E6: 4500 | F6: 6600 | G6: Sim

Sheet Despesas
A1: Despesas Dedutíveis
A2: Registre saúde, educação, previdência privada e demais deduções. A linha 6 é um exemplo.
A3: ⬅ Voltar ao Menu
A5: Data | B5: Prestador / Beneficiário | C5: CNPJ/CPF (só números) | D5: Categoria | E5: Valor pago (R$) | F5: Comprovante guardado?
A6: 45731 | B6: Clínica Exemplo | C6: 00000000000191 | D6: Saúde | E6: 850 | F6: Sim

Sheet Bens e Direitos
A1: Bens e Direitos
A2: Informe a situação em 31/12 do ano anterior e do ano-base. A linha 6 é um exemplo.
A3: ⬅ Voltar ao Menu
A5: Descrição do bem | B5: Grupo | C5: Discriminação / Localização | D5: Situação em 31/12 (ano anterior) R$ | E5: Situação em 31/12 (ano-base) R$ | F5: Variação (R$)
A6: Apartamento residencial | B6: Imóvel | C6: Rua Exemplo, 100 - Serra/ES | D6: 250000 | E6: 250000 | F6: =IF(AND(D6="",E6=""),"",E6-D6) -> 0
F7: =IF(AND(D7="",E7=""),"",E7-D7)
F8: =IF(AND(D8="",E8=""),"",E8-D8)
F9: =IF(AND(D9="",E9=""),"",E9-D9)
F10: =IF(AND(D10="",E10=""),"",E10-D10)
F11: =IF(AND(D11="",E11=""),"",E11-D11)
F12: =IF(AND(D12="",E12=""),"",E12-D12)
F13: =IF(AND(D13="",E13=""),"",E13-D13)
F14: =IF(AND(D14="",E14=""),"",E14-D14)
F15: =IF(AND(D15="",E15=""),"",E15-D15)
F16: =IF(AND(D16="",E16=""),"",E16-D16)
F17: =IF(AND(D17="",E17=""),"",E17-D17)
F18: =IF(AND(D18="",E18=""),"",E18-D18)
... F105: =IF(AND(D105="",E105=""),"",E105-D105)

Sheet Dívidas
A1: Dívidas e Ônus Reais
A2: Financiamentos, empréstimos e outras dívidas. A linha 6 é um exemplo.
A3: ⬅ Voltar ao Menu
A5: Credor / Descrição | B5: Saldo 31/12 (ano anterior) R$ | C5: Saldo 31/12 (ano-base) R$ | D5: Pago no ano R$ | E5: Observação
A6: Financiamento Exemplo S.A. | B6: 80000 | C6: 72000 | D6: 12000 | E6: Financiamento imobiliário

Sheet Checklist
A1: Checklist de Documentos
A2: Acompanhe o que já foi reunido. O percentual concluído considera 'Conferido'.
A3: ⬅ Voltar ao Menu
A5: Documento | B5: Status | C5: Onde obter
A6: Informe de rendimentos (empresas / INSS) | B6: Pendente | C6: Site/RH da fonte pagadora ou Meu INSS
A7: Informe de rendimentos bancários | B7: Pendente | C7: Aplicativo ou internet banking
A8: Recibos de despesas médicas | B8: Pendente | C8: Prestadores de saúde
A9: Comprovantes de educação | B9: Pendente | C9: Instituição de ensino
A10: Extrato de corretora / investimentos | B10: Pendente | C10: Corretora ou B3
A11: Documentos de bens (escrituras, CRLV) | B11: Pendente | C11: Cartório, Detran
A12: Contratos de financiamento | B12: Pendente | C12: Banco credor
A13: Recibo da declaração do ano anterior | B13: Pendente | C13: Receita Federal / e-CAC
A15: % conferido | B15: =COUNTIF(B6:B13,"Conferido")/COUNTA(A6:A13) -> 0

Sheet Resumo
A1: Resumo da Declaração
A2: Totais calculados automaticamente a partir das demais abas. Não digite nesta aba.
A3: ⬅ Voltar ao Menu
A5: Indicador | B5: Valor | C5: Observação
A6: Total de rendimentos brutos | B6: =SUM(Rendimentos!D6:D205) -> 60000
A7: Total de IRRF retido | B7: =SUM(Rendimentos!E6:E205) -> 4500 | C7: Imposto já pago na fonte
A8: Total de INSS / previdência oficial | B8: =SUM(Rendimentos!F6:F205) -> 6600
A9: Despesas com saúde | B9: =SUMIFS(Despesas!E6:E205,Despesas!D6:D205,"Saúde") -> 850 | C9: Sem limite de dedução
A10: Despesas com educação (pago) | B10: =SUMIFS(Despesas!E6:E205,Despesas!D6:D205,"Educação") -> 0
A11: Educação dedutível (respeitando limite) | B11: =MIN(B10,Listas!B17) -> 0 | C11: Limite editável na aba Listas
A12: Previdência privada (PGBL) | B12: =SUMIFS(Despesas!E6:E205,Despesas!D6:D205,"Previdência privada (PGBL)") -> 0 | C12: Sujeita a limite de 12% da renda bruta
A13: Pensão alimentícia | B13: =SUMIFS(Despesas!E6:E205,Despesas!D6:D205,"Pensão alimentícia") -> 0
A14: Total de bens (ano-base) | B14: =SUM('Bens e Direitos'!E6:E105) -> 250000
A15: Total de bens (ano anterior) | B15: =SUM('Bens e Direitos'!D6:D105) -> 250000
A16: Total de dívidas (ano-base) | B16: =SUM(Dívidas!C6:C55) -> 72000
A17: Patrimônio líquido (ano-base) | B17: =B14-B16 -> 178000 | C17: Bens menos dívidas
A18: Fontes pagadoras cadastradas | B18: =COUNTA(Rendimentos!A6:A205) -> 1
A19: Documentos conferidos | B19: =Checklist!B15 -> 0
A21: Aviso: esta planilha organiza informações e não substitui o programa oficial da Receita Federal nem orientação contábil.

Sheet Listas
A1: Listas de Apoio
A2: Fonte das listas suspensas (validação de dados). Edite aqui para atualizar os menus das outras abas.
A3: ⬅ Voltar ao Menu
A5: Tipo de rendimento | B5: Categoria de despesa | C5: Grupo de bem | D5: Status do documento | E5: Sim/Não
A6: Salário / Trabalho assalariado | B6: Saúde | C6: Imóvel | D6: Pendente | E6: Sim
A7: Pró-labore | B7: Educação | C7: Veículo | D7: Recebido | E7: Não
A8: Aposentadoria / Pensão | B8: Previdência privada (PGBL) | C8: Conta bancária | D8: Conferido
A9: Aluguéis | B9: Pensão alimentícia | C9: Aplicação financeira
A10: Trabalho autônomo | B10: Livro-caixa | C10: Ações / Fundos
A11: Rendimento de investimentos | B11: Outras | C11: Criptoativos
A12: Rendimento isento | C12: Outros bens
A13: Outros
A16: Parâmetro editável
A17: Limite anual de dedução com Educação (R$) | B17: 3561.5
A18: Valor informado pelo autor com base na regra vigente do IRPF; confirme no site da Receita Federal a cada ano-base.
