Workbook
Name salario: 'Simulador'!$B$5
Name aporte: 'Simulador'!$B$6
Name prazo_anos: 'Simulador'!$B$7
Name taxa_mensal: 'Simulador'!$B$8

Sheet Simulador
A1: SIMULADOR DE INVESTIMENTOS EM FUNDOS IMOBILIÁRIOS
A2: Simulação educacional de aportes mensais, patrimônio futuro e dividendos estimados
A4: CONFIGURAÇÕES E RESULTADOS
A5: Salário mensal | B5: 3000 | C5: Entrada — exemplo
A6: Aporte mensal | B6: 500 | C6: Entrada — exemplo
A7: Prazo do investimento (anos) | B7: 10 | C7: Entrada — exemplo
A8: Rendimento mensal estimado | B8: 0.008 | C8: Entrada — exemplo
A9: Perfil do investidor | B9: Moderado | C9: Lista suspensa
A11: INDICADORES PRINCIPAIS
A12: Sugestão de aporte (30% do salário) | B12: =B5*30% | C12: Calculado automaticamente
A13: Patrimônio acumulado estimado | B13: =FV(B8,B7*12,-B6,0,0) | C13: Aportes no fim de cada mês
A14: Dividendos mensais estimados | B14: =B13*B8 | C14: Usa a taxa mensal informada como hipótese
A16: PROJEÇÃO POR PRAZO
A17: Prazo (anos) | B17: Patrimônio estimado | C17: Dividendos/mês estimados
A18: 2 | B18: =FV($B$8,A18*12,-$B$6,0,0) | C18: =B18*$B$8
A19: 5 | B19: =FV($B$8,A19*12,-$B$6,0,0) | C19: =B19*$B$8
A20: 10 | B20: =FV($B$8,A20*12,-$B$6,0,0) | C20: =B20*$B$8
A21: 20 | B21: =FV($B$8,A21*12,-$B$6,0,0) | C21: =B21*$B$8
A22: 30 | B22: =FV($B$8,A22*12,-$B$6,0,0) | C22: =B22*$B$8
A25: DISTRIBUIÇÃO DO APORTE POR TIPO DE FUNDO
A26: Tipo de fundo | B26: Percentual | C26: Aporte mensal
A27: Tijolo | B27: =IFERROR(VLOOKUP($B$9&"|"&A27,Apoio!$A$2:$D$19,4,FALSE),0) | C27: =$B$6*B27
A28: Papel | B28: =IFERROR(VLOOKUP($B$9&"|"&A28,Apoio!$A$2:$D$19,4,FALSE),0) | C28: =$B$6*B28
A29: Híbridos | B29: =IFERROR(VLOOKUP($B$9&"|"&A29,Apoio!$A$2:$D$19,4,FALSE),0) | C29: =$B$6*B29
A30: Fundos de fundos (FOFs) | B30: =IFERROR(VLOOKUP($B$9&"|"&A30,Apoio!$A$2:$D$19,4,FALSE),0) | C30: =$B$6*B30
A31: Desenvolvimento | B31: =IFERROR(VLOOKUP($B$9&"|"&A31,Apoio!$A$2:$D$19,4,FALSE),0) | C31: =$B$6*B31
A32: Outros | B32: =IFERROR(VLOOKUP($B$9&"|"&A32,Apoio!$A$2:$D$19,4,FALSE),0) | C32: =$B$6*B32
A33: TOTAL | B33: =SUM(B27:B32) | C33: =SUM(C27:C32)
A35: Aviso: simulação hipotética para fins educacionais. Rendimentos e dividendos não são garantidos; isto não é recomendação de investimento.

Sheet Apoio
A1: Chave composta | B1: Perfil | C1: Tipo de fundo | D1: Percentual | F1: Perfis disponíveis
A2: =B2&"|"&C2 | B2: Conservador | C2: Tijolo | D2: 0.15 | F2: Conservador
A3: =B3&"|"&C3 | B3: Conservador | C3: Papel | D3: 0.35 | F3: Moderado
A4: =B4&"|"&C4 | B4: Conservador | C4: Híbridos | D4: 0.15 | F4: Arrojado
A5: =B5&"|"&C5 | B5: Conservador | C5: Fundos de fundos (FOFs) | D5: 0.2
A6: =B6&"|"&C6 | B6: Conservador | C6: Desenvolvimento | D6: 0.05 | F6: Notas
A7: =B7&"|"&C7 | B7: Conservador | C7: Outros | D7: 0.1 | F7: Percentuais fictícios para demonstrar PROCV e chave composta.
A8: =B8&"|"&C8 | B8: Moderado | C8: Tijolo | D8: 0.3
A9: =B9&"|"&C9 | B9: Moderado | C9: Papel | D9: 0.25
A10: =B10&"|"&C10 | B10: Moderado | C10: Híbridos | D10: 0.15
A11: =B11&"|"&C11 | B11: Moderado | C11: Fundos de fundos (FOFs) | D11: 0.1
A12: =B12&"|"&C12 | B12: Moderado | C12: Desenvolvimento | D12: 0.1
A13: =B13&"|"&C13 | B13: Moderado | C13: Outros | D13: 0.1
A14: =B14&"|"&C14 | B14: Arrojado | C14: Tijolo | D14: 0.35
A15: =B15&"|"&C15 | B15: Arrojado | C15: Papel | D15: 0.15
A16: =B16&"|"&C16 | B16: Arrojado | C16: Híbridos | D16: 0.1
A17: =B17&"|"&C17 | B17: Arrojado | C17: Fundos de fundos (FOFs) | D17: 0.05
A18: =B18&"|"&C18 | B18: Arrojado | C18: Desenvolvimento | D18: 0.25
A19: =B19&"|"&C19 | B19: Arrojado | C19: Outros | D19: 0.1
A21: Como funciona
A22: 1. A chave composta combina Perfil e Tipo de fundo para localizar uma combinação única.
A23: 2. O PROCV procura a chave na coluna A e retorna o percentual da coluna D.
A24: 3. Cada perfil soma 100%; os percentuais são apenas exemplos didáticos.
A25: 4. A função VF calcula o valor futuro de aportes mensais constantes, supondo taxa mensal constante.
